numpytimebuilder/__init__.py
numpytimebuilder/compat.py
numpytimebuilder/constants.py
numpytimebuilder/util.py
numpytimebuilder/version.py
numpytimebuilder/tests/__init__.py
numpytimebuilder/tests/test_init.py
numpytimebuilder/tests/test_util.py
numpytimebuilder-0.4.3.dist-info/licenses/LICENSE
numpytimebuilder-0.4.3.dist-info/METADATA
numpytimebuilder-0.4.3.dist-info/WHEEL
numpytimebuilder-0.4.3.dist-info/top_level.txt
numpytimebuilder-0.4.3.dist-info/RECORD
